{
	"info": {
		"_postman_id": "3ef10db0-c68d-4c88-9d90-217de6956254",
		"name": "Go-fiber-HRMS-mongo",
		"schema": "https://schema.getpostman.com/json/collection/v2.1.0/collection.json",
		"_exporter_id": "19312868"
	},
	"item": [
		{
			"name": "GET ALL EMPLOYEES",
			"request": {
				"method": "GET",
				"header": [],
				"url": {
					"raw": "http://localhost:3000/employee",
					"protocol": "http",
					"host": [
						"localhost"
					],
					"port": "3000",
					"path": [
						"employee"
					]
				}
			},
			"response": []
		},
		{
			"name": "ADD EMPLOYEE",
			"request": {
				"method": "POST",
				"header": [],
				"url": {
					"raw": "http://localhost:3000/employee",
					"protocol": "http",
					"host": [
						"localhost"
					],
					"port": "3000",
					"path": [
						"employee"
					]
				}
			},
			"response": []
		},
		{
			"name": "EDIT AN EMPLOYEE",
			"request": {
				"method": "PUT",
				"header": [],
				"url": {
					"raw": "http://localhost:3000/employee/:id",
					"protocol": "http",
					"host": [
						"localhost"
					],
					"port": "3000",
					"path": [
						"employee",
						":id"
					],
					"variable": [
						{
							"key": "id",
							"value": "1"
						}
					]
				}
			},
			"response": []
		},
		{
			"name": "DELETE AN EMPLOYEE",
			"request": {
				"method": "DELETE",
				"header": [],
				"url": {
					"raw": "http://localhost:3000/employee/:id",
					"protocol": "http",
					"host": [
						"localhost"
					],
					"port": "3000",
					"path": [
						"employee",
						":id"
					],
					"variable": [
						{
							"key": "id",
							"value": "1"
						}
					]
				}
			},
			"response": []
		}
	]
}